smallworld/__init__.py
smallworld/helpers.py
smallworld/logging.py
smallworld/py.typed
smallworld/utils.py
smallworld/analyses/__init__.py
smallworld/analyses/analysis.py
smallworld/analyses/code_coverage.py
smallworld/analyses/colorizer.py
smallworld/analyses/colorizer_def_use.py
smallworld/analyses/colorizer_summary.py
smallworld/analyses/coverage_frontier.py
smallworld/analyses/trace_execution.py
smallworld/analyses/trace_execution_types.py
smallworld/analyses/field_detection/__init__.py
smallworld/analyses/field_detection/field_analysis.py
smallworld/analyses/field_detection/guards.py
smallworld/analyses/field_detection/hints.py
smallworld/analyses/field_detection/malloc.py
smallworld/analyses/forced_exec/__init__.py
smallworld/analyses/forced_exec/forced_exec.py
smallworld/analyses/underlays/__init__.py
smallworld/analyses/underlays/basic.py
smallworld/analyses/underlays/underlay.py
smallworld/analyses/unstable/__init__.py
smallworld/analyses/unstable/angr_nwbt.py
smallworld/analyses/unstable/code_coverage.py
smallworld/analyses/unstable/code_reachable.py
smallworld/analyses/unstable/control_flow_tracer.py
smallworld/analyses/unstable/pointer_finder.py
smallworld/analyses/unstable/angr/__init__.py
smallworld/analyses/unstable/angr/base.py
smallworld/analyses/unstable/angr/divergence.py
smallworld/analyses/unstable/angr/model.py
smallworld/analyses/unstable/angr/nwbt.py
smallworld/analyses/unstable/angr/typedefs.py
smallworld/analyses/unstable/angr/utils.py
smallworld/analyses/unstable/angr/visitor.py
smallworld/analyses/unstable/utils/tui.py
smallworld/arch/__init__.py
smallworld/arch/aarch64_arch.py
smallworld/arch/amd64_arch.py
smallworld/arch/i386_arch.py
smallworld/emulators/__init__.py
smallworld/emulators/emulator.py
smallworld/emulators/hookable.py
smallworld/emulators/angr/__init__.py
smallworld/emulators/angr/angr.py
smallworld/emulators/angr/default.py
smallworld/emulators/angr/exceptions.py
smallworld/emulators/angr/factory.py
smallworld_re-2.0.2.dist-info/licenses/LICENSE.txt
smallworld_re-2.0.2.dist-info/METADATA
smallworld_re-2.0.2.dist-info/WHEEL
smallworld_re-2.0.2.dist-info/entry_points.txt
smallworld_re-2.0.2.dist-info/top_level.txt
smallworld_re-2.0.2.dist-info/RECORD
