Metadata-Version: 2.4
Name: smallworld-re
Version: 2.0.2
Summary: An emulation stack tracking library
Author: MIT Lincoln Laboratory
Author-email: smallworld@ll.mit.edu
License: MIT License
Project-URL: Homepage, https://github.com/smallworld-re/smallworld
Project-URL: Issues, https://github.com/smallworld-re/smallworld/issues
Requires-Python: >=3.10
License-File: LICENSE.txt
Requires-Dist: angr==9.2.137
Requires-Dist: capstone==5.0.3
Requires-Dist: jsons==1.6.3
Requires-Dist: lief==0.17.0
Requires-Dist: pyhidra==1.3.0
Requires-Dist: pypcode==3.0
Requires-Dist: unicorn==2.0.1.post1
Provides-Extra: development
Requires-Dist: black; extra == "development"
Requires-Dist: isort; extra == "development"
Requires-Dist: flake8; extra == "development"
Requires-Dist: mypy; extra == "development"
Requires-Dist: pip-tools; extra == "development"
Requires-Dist: pre-commit; extra == "development"
Requires-Dist: sphinx; extra == "development"
Requires-Dist: sphinxcontrib-programoutput; extra == "development"
Requires-Dist: jupyterlab; extra == "development"
Requires-Dist: notebook; extra == "development"
Requires-Dist: timeout-decorator; extra == "development"
Dynamic: license-file
